[
	{
		"sysrundate" : "2025-07-06",
		"order_id" : 1002,
		"lat" : "19.102999",
		"lon" : "72.861701",
		"courier_id" : "C1002",
		"customer_id" : "U221",
		"gps_ts" : null,
		"delivery_ts" : null,
		"sameday_delivery_status" : "Not Started"
	},
	{
		"sysrundate" : "2025-07-06",
		"order_id" : 1040,
		"lat" : "18.936395",
		"lon" : "72.959317",
		"courier_id" : "C1040",
		"customer_id" : "U464",
		"gps_ts" : "2025-07-06 07:05:00",
		"delivery_ts" : "2025-07-06 07:32:00",
		"sameday_delivery_status" : "Delivered"
	},
	{
		"sysrundate" : "2025-07-06",
		"order_id" : 1163,
		"lat" : "19.022763",
		"lon" : "72.839861",
		"courier_id" : "C1163",
		"customer_id" : "U927",
		"gps_ts" : "2025-07-06 10:02:00",
		"delivery_ts" : "2025-07-06 10:29:00",
		"sameday_delivery_status" : "Cancelled"
	},
	{
		"sysrundate" : "2025-07-06",
		"order_id" : 1180,
		"lat" : "19.095361",
		"lon" : "72.821125",
		"courier_id" : "C1180",
		"customer_id" : "U297",
		"gps_ts" : "2025-07-06 13:33:00",
		"delivery_ts" : "2025-07-06 13:58:00",
		"sameday_delivery_status" : "Cancelled"
	},
	{
		"sysrundate" : "2025-07-06",
		"order_id" : 1184,
		"lat" : "19.115047",
		"lon" : "72.840442",
		"courier_id" : "C1184",
		"customer_id" : "U355",
		"gps_ts" : "2025-07-06 13:27:00",
		"delivery_ts" : "2025-07-06 13:56:00",
		"sameday_delivery_status" : "Delivered"
	},
	{
		"sysrundate" : "2025-07-06",
		"order_id" : 1250,
		"lat" : "18.953132",
		"lon" : "72.95636",
		"courier_id" : "C1250",
		"customer_id" : "U974",
		"gps_ts" : "2025-07-06 06:42:00",
		"delivery_ts" : "2025-07-06 07:32:00",
		"sameday_delivery_status" : "Delivered"
	},
	{
		"sysrundate" : "2025-07-06",
		"order_id" : 1257,
		"lat" : "19.206227",
		"lon" : "72.98046",
		"courier_id" : "C1257",
		"customer_id" : "U993",
		"gps_ts" : "2025-07-06 16:47:00",
		"delivery_ts" : "2025-07-06 17:10:00",
		"sameday_delivery_status" : "Delivered"
	},
	{
		"sysrundate" : "2025-07-06",
		"order_id" : 1265,
		"lat" : "19.086882",
		"lon" : "72.885387",
		"courier_id" : "C1265",
		"customer_id" : "U939",
		"gps_ts" : "2025-07-06 00:23:00",
		"delivery_ts" : "2025-07-06 00:49:00",
		"sameday_delivery_status" : "Delivered"
	},
	{
		"sysrundate" : "2025-07-06",
		"order_id" : 1291,
		"lat" : "19.17498",
		"lon" : "72.83821",
		"courier_id" : "C1291",
		"customer_id" : "U223",
		"gps_ts" : "2025-07-06 01:26:00",
		"delivery_ts" : "2025-07-06 01:51:00",
		"sameday_delivery_status" : "Delivered"
	},
	{
		"sysrundate" : "2025-07-06",
		"order_id" : 1409,
		"lat" : "19.141467",
		"lon" : "72.831572",
		"courier_id" : "C1409",
		"customer_id" : "U570",
		"gps_ts" : "2025-07-06 08:58:00",
		"delivery_ts" : "2025-07-06 09:01:00",
		"sameday_delivery_status" : "Cancelled"
	},
	{
		"sysrundate" : "2025-07-06",
		"order_id" : 1418,
		"lat" : "18.979207",
		"lon" : "72.759383",
		"courier_id" : "C1418",
		"customer_id" : "U450",
		"gps_ts" : "2025-07-06 18:53:00",
		"delivery_ts" : "2025-07-06 18:50:00",
		"sameday_delivery_status" : "Picked_up"
	},
	{
		"sysrundate" : "2025-07-06",
		"order_id" : 1434,
		"lat" : "19.155548",
		"lon" : "72.814121",
		"courier_id" : "C1434",
		"customer_id" : "U759",
		"gps_ts" : "2025-07-06 11:20:00",
		"delivery_ts" : "2025-07-06 11:57:00",
		"sameday_delivery_status" : "Delivered"
	},
	{
		"sysrundate" : "2025-07-06",
		"order_id" : 1442,
		"lat" : "19.194363",
		"lon" : "72.921932",
		"courier_id" : "C1442",
		"customer_id" : "U758",
		"gps_ts" : null,
		"delivery_ts" : null,
		"sameday_delivery_status" : "Not Started"
	},
	{
		"sysrundate" : "2025-07-06",
		"order_id" : 1508,
		"lat" : "19.145949",
		"lon" : "72.775454",
		"courier_id" : "C1508",
		"customer_id" : "U915",
		"gps_ts" : null,
		"delivery_ts" : null,
		"sameday_delivery_status" : "Not Started"
	},
	{
		"sysrundate" : "2025-07-06",
		"order_id" : 1542,
		"lat" : "19.081704",
		"lon" : "72.92124",
		"courier_id" : "C1542",
		"customer_id" : "U993",
		"gps_ts" : "2025-07-06 04:26:00",
		"delivery_ts" : "2025-07-06 05:09:00",
		"sameday_delivery_status" : "Ontheway"
	},
	{
		"sysrundate" : "2025-07-06",
		"order_id" : 1551,
		"lat" : "19.269117",
		"lon" : "72.88181",
		"courier_id" : "C1551",
		"customer_id" : "U232",
		"gps_ts" : null,
		"delivery_ts" : null,
		"sameday_delivery_status" : "Not Started"
	},
	{
		"sysrundate" : "2025-07-06",
		"order_id" : 1571,
		"lat" : "19.156715",
		"lon" : "72.849162",
		"courier_id" : "C1571",
		"customer_id" : "U611",
		"gps_ts" : null,
		"delivery_ts" : null,
		"sameday_delivery_status" : "Not Started"
	},
	{
		"sysrundate" : "2025-07-06",
		"order_id" : 1574,
		"lat" : "19.013589",
		"lon" : "72.773716",
		"courier_id" : "C1574",
		"customer_id" : "U698",
		"gps_ts" : "2025-07-06 10:19:00",
		"delivery_ts" : "2025-07-06 11:09:00",
		"sameday_delivery_status" : "Cancelled"
	},
	{
		"sysrundate" : "2025-07-06",
		"order_id" : 1613,
		"lat" : "19.246935",
		"lon" : "72.893216",
		"courier_id" : "C1613",
		"customer_id" : "U763",
		"gps_ts" : "2025-07-06 00:41:00",
		"delivery_ts" : "2025-07-06 00:38:00",
		"sameday_delivery_status" : "Delivered"
	},
	{
		"sysrundate" : "2025-07-06",
		"order_id" : 1654,
		"lat" : "19.178823",
		"lon" : "72.802802",
		"courier_id" : "C1654",
		"customer_id" : "U472",
		"gps_ts" : "2025-07-06 12:48:00",
		"delivery_ts" : "2025-07-06 13:23:00",
		"sameday_delivery_status" : "Delivered"
	},
	{
		"sysrundate" : "2025-07-06",
		"order_id" : 1657,
		"lat" : "19.235452",
		"lon" : "72.785469",
		"courier_id" : "C1657",
		"customer_id" : "U642",
		"gps_ts" : "2025-07-06 15:53:00",
		"delivery_ts" : "2025-07-06 16:11:00",
		"sameday_delivery_status" : "Delivered"
	},
	{
		"sysrundate" : "2025-07-06",
		"order_id" : 1778,
		"lat" : "18.937879",
		"lon" : "72.842761",
		"courier_id" : "C1778",
		"customer_id" : "U627",
		"gps_ts" : null,
		"delivery_ts" : null,
		"sameday_delivery_status" : "Not Started"
	},
	{
		"sysrundate" : "2025-07-06",
		"order_id" : 1910,
		"lat" : "19.016243",
		"lon" : "72.828256",
		"courier_id" : "C1910",
		"customer_id" : "U867",
		"gps_ts" : "2025-07-06 12:17:00",
		"delivery_ts" : "2025-07-06 12:21:00",
		"sameday_delivery_status" : "Delivered"
	},
	{
		"sysrundate" : "2025-07-06",
		"order_id" : 1945,
		"lat" : "19.287062",
		"lon" : "72.959239",
		"courier_id" : "C1945",
		"customer_id" : "U376",
		"gps_ts" : null,
		"delivery_ts" : null,
		"sameday_delivery_status" : "Not Started"
	},
	{
		"sysrundate" : "2025-07-06",
		"order_id" : 1979,
		"lat" : "19.047291",
		"lon" : "72.799832",
		"courier_id" : "C1979",
		"customer_id" : "U689",
		"gps_ts" : null,
		"delivery_ts" : null,
		"sameday_delivery_status" : "Not Started"
	},
	{
		"sysrundate" : "2025-07-06",
		"order_id" : 1982,
		"lat" : "19.167471",
		"lon" : "72.825721",
		"courier_id" : "C1982",
		"customer_id" : "U626",
		"gps_ts" : null,
		"delivery_ts" : null,
		"sameday_delivery_status" : "Not Started"
	},
	{
		"sysrundate" : "2025-07-06",
		"order_id" : 2019,
		"lat" : "13.151122",
		"lon" : "80.248133",
		"courier_id" : "C2019",
		"customer_id" : "U683",
		"gps_ts" : "2025-07-06 07:08:00",
		"delivery_ts" : "2025-07-06 07:32:00",
		"sameday_delivery_status" : "Cancelled"
	},
	{
		"sysrundate" : "2025-07-06",
		"order_id" : 2162,
		"lat" : "13.023401",
		"lon" : "80.237191",
		"courier_id" : "C2162",
		"customer_id" : "U341",
		"gps_ts" : null,
		"delivery_ts" : null,
		"sameday_delivery_status" : "Not Started"
	},
	{
		"sysrundate" : "2025-07-06",
		"order_id" : 2191,
		"lat" : "13.178813",
		"lon" : "80.233269",
		"courier_id" : "C2191",
		"customer_id" : "U216",
		"gps_ts" : null,
		"delivery_ts" : null,
		"sameday_delivery_status" : "Not Started"
	},
	{
		"sysrundate" : "2025-07-06",
		"order_id" : 2275,
		"lat" : "12.927208",
		"lon" : "80.24495",
		"courier_id" : "C2275",
		"customer_id" : "U900",
		"gps_ts" : "2025-07-06 15:01:00",
		"delivery_ts" : "2025-07-06 15:24:00",
		"sameday_delivery_status" : "Ontheway"
	},
	{
		"sysrundate" : "2025-07-06",
		"order_id" : 2310,
		"lat" : "12.963665",
		"lon" : "80.157403",
		"courier_id" : "C2310",
		"customer_id" : "U347",
		"gps_ts" : "2025-07-06 15:42:00",
		"delivery_ts" : "2025-07-06 16:00:00",
		"sameday_delivery_status" : "Delivered"
	},
	{
		"sysrundate" : "2025-07-06",
		"order_id" : 2350,
		"lat" : "13.032607",
		"lon" : "80.275063",
		"courier_id" : "C2350",
		"customer_id" : "U187",
		"gps_ts" : "2025-07-06 10:11:00",
		"delivery_ts" : "2025-07-06 10:23:00",
		"sameday_delivery_status" : "Ontheway"
	},
	{
		"sysrundate" : "2025-07-06",
		"order_id" : 2381,
		"lat" : "13.060078",
		"lon" : "80.16036",
		"courier_id" : "C2381",
		"customer_id" : "U884",
		"gps_ts" : "2025-07-06 05:43:00",
		"delivery_ts" : "2025-07-06 05:42:00",
		"sameday_delivery_status" : "Delivered"
	},
	{
		"sysrundate" : "2025-07-06",
		"order_id" : 2424,
		"lat" : "13.126256",
		"lon" : "80.167609",
		"courier_id" : "C2424",
		"customer_id" : "U449",
		"gps_ts" : null,
		"delivery_ts" : null,
		"sameday_delivery_status" : "Not Started"
	},
	{
		"sysrundate" : "2025-07-06",
		"order_id" : 2438,
		"lat" : "13.121247",
		"lon" : "80.296992",
		"courier_id" : "C2438",
		"customer_id" : "U562",
		"gps_ts" : "2025-07-06 11:16:00",
		"delivery_ts" : "2025-07-06 12:04:00",
		"sameday_delivery_status" : "Cancelled"
	},
	{
		"sysrundate" : "2025-07-06",
		"order_id" : 2442,
		"lat" : "12.979791",
		"lon" : "80.246763",
		"courier_id" : "C2442",
		"customer_id" : "U163",
		"gps_ts" : "2025-07-06 16:56:00",
		"delivery_ts" : "2025-07-06 16:54:00",
		"sameday_delivery_status" : "Cancelled"
	},
	{
		"sysrundate" : "2025-07-06",
		"order_id" : 2445,
		"lat" : "13.160329",
		"lon" : "80.213883",
		"courier_id" : "C2445",
		"customer_id" : "U199",
		"gps_ts" : "2025-07-06 13:32:00",
		"delivery_ts" : "2025-07-06 14:19:00",
		"sameday_delivery_status" : "Cancelled"
	},
	{
		"sysrundate" : "2025-07-06",
		"order_id" : 2475,
		"lat" : "12.935171",
		"lon" : "80.204045",
		"courier_id" : "C2475",
		"customer_id" : "U776",
		"gps_ts" : "2025-07-06 16:30:00",
		"delivery_ts" : "2025-07-06 16:56:00",
		"sameday_delivery_status" : "Cancelled"
	},
	{
		"sysrundate" : "2025-07-06",
		"order_id" : 2485,
		"lat" : "13.063137",
		"lon" : "80.151195",
		"courier_id" : "C2485",
		"customer_id" : "U892",
		"gps_ts" : "2025-07-06 10:08:00",
		"delivery_ts" : "2025-07-06 10:13:00",
		"sameday_delivery_status" : "Ontheway"
	},
	{
		"sysrundate" : "2025-07-06",
		"order_id" : 2492,
		"lat" : "13.177779",
		"lon" : "80.280062",
		"courier_id" : "C2492",
		"customer_id" : "U717",
		"gps_ts" : "2025-07-06 12:55:00",
		"delivery_ts" : "2025-07-06 13:24:00",
		"sameday_delivery_status" : "Delivered"
	},
	{
		"sysrundate" : "2025-07-06",
		"order_id" : 2522,
		"lat" : "13.117769",
		"lon" : "80.183254",
		"courier_id" : "C2522",
		"customer_id" : "U225",
		"gps_ts" : "2025-07-06 12:55:00",
		"delivery_ts" : "2025-07-06 13:04:00",
		"sameday_delivery_status" : "Ontheway"
	},
	{
		"sysrundate" : "2025-07-06",
		"order_id" : 2534,
		"lat" : "12.908694",
		"lon" : "80.22212",
		"courier_id" : "C2534",
		"customer_id" : "U284",
		"gps_ts" : "2025-07-06 14:00:00",
		"delivery_ts" : "2025-07-06 14:33:00",
		"sameday_delivery_status" : "Cancelled"
	},
	{
		"sysrundate" : "2025-07-06",
		"order_id" : 2584,
		"lat" : "13.129793",
		"lon" : "80.268127",
		"courier_id" : "C2584",
		"customer_id" : "U784",
		"gps_ts" : null,
		"delivery_ts" : null,
		"sameday_delivery_status" : "Not Started"
	},
	{
		"sysrundate" : "2025-07-06",
		"order_id" : 2597,
		"lat" : "13.011937",
		"lon" : "80.161506",
		"courier_id" : "C2597",
		"customer_id" : "U887",
		"gps_ts" : "2025-07-06 00:47:00",
		"delivery_ts" : "2025-07-06 00:54:00",
		"sameday_delivery_status" : "Delivered"
	},
	{
		"sysrundate" : "2025-07-06",
		"order_id" : 2599,
		"lat" : "13.016731",
		"lon" : "80.27729",
		"courier_id" : "C2599",
		"customer_id" : "U804",
		"gps_ts" : null,
		"delivery_ts" : null,
		"sameday_delivery_status" : "Not Started"
	},
	{
		"sysrundate" : "2025-07-06",
		"order_id" : 2627,
		"lat" : "13.121917",
		"lon" : "80.210887",
		"courier_id" : "C2627",
		"customer_id" : "U803",
		"gps_ts" : "2025-07-06 03:37:00",
		"delivery_ts" : "2025-07-06 03:54:00",
		"sameday_delivery_status" : "Cancelled"
	},
	{
		"sysrundate" : "2025-07-06",
		"order_id" : 2633,
		"lat" : "13.121659",
		"lon" : "80.249648",
		"courier_id" : "C2633",
		"customer_id" : "U652",
		"gps_ts" : "2025-07-06 03:28:00",
		"delivery_ts" : "2025-07-06 03:37:00",
		"sameday_delivery_status" : "Cancelled"
	},
	{
		"sysrundate" : "2025-07-06",
		"order_id" : 2714,
		"lat" : "13.028884",
		"lon" : "80.197455",
		"courier_id" : "C2714",
		"customer_id" : "U349",
		"gps_ts" : null,
		"delivery_ts" : null,
		"sameday_delivery_status" : "Not Started"
	},
	{
		"sysrundate" : "2025-07-06",
		"order_id" : 2715,
		"lat" : "12.940403",
		"lon" : "80.268974",
		"courier_id" : "C2715",
		"customer_id" : "U132",
		"gps_ts" : "2025-07-06 14:43:00",
		"delivery_ts" : "2025-07-06 14:52:00",
		"sameday_delivery_status" : "Ontheway"
	},
	{
		"sysrundate" : "2025-07-06",
		"order_id" : 2801,
		"lat" : "12.909086",
		"lon" : "80.195905",
		"courier_id" : "C2801",
		"customer_id" : "U408",
		"gps_ts" : "2025-07-06 18:35:00",
		"delivery_ts" : "2025-07-06 19:08:00",
		"sameday_delivery_status" : "Picked_up"
	},
	{
		"sysrundate" : "2025-07-06",
		"order_id" : 2875,
		"lat" : "13.045552",
		"lon" : "80.202175",
		"courier_id" : "C2875",
		"customer_id" : "U870",
		"gps_ts" : "2025-07-06 15:05:00",
		"delivery_ts" : "2025-07-06 15:24:00",
		"sameday_delivery_status" : "Cancelled"
	},
	{
		"sysrundate" : "2025-07-06",
		"order_id" : 2902,
		"lat" : "13.1518",
		"lon" : "80.288342",
		"courier_id" : "C2902",
		"customer_id" : "U483",
		"gps_ts" : "2025-07-06 02:39:00",
		"delivery_ts" : "2025-07-06 02:54:00",
		"sameday_delivery_status" : "Cancelled"
	},
	{
		"sysrundate" : "2025-07-06",
		"order_id" : 2967,
		"lat" : "13.110044",
		"lon" : "80.219099",
		"courier_id" : "C2967",
		"customer_id" : "U767",
		"gps_ts" : "2025-07-06 09:46:00",
		"delivery_ts" : "2025-07-06 10:25:00",
		"sameday_delivery_status" : "Ontheway"
	},
	{
		"sysrundate" : "2025-07-06",
		"order_id" : 3260,
		"lat" : "22.578059",
		"lon" : "88.402333",
		"courier_id" : "C3260",
		"customer_id" : "U324",
		"gps_ts" : "2025-07-06 09:09:00",
		"delivery_ts" : "2025-07-06 10:06:00",
		"sameday_delivery_status" : "Ontheway"
	},
	{
		"sysrundate" : "2025-07-06",
		"order_id" : 3473,
		"lat" : "22.566224",
		"lon" : "88.326403",
		"courier_id" : "C3473",
		"customer_id" : "U972",
		"gps_ts" : null,
		"delivery_ts" : null,
		"sameday_delivery_status" : "Not Started"
	},
	{
		"sysrundate" : "2025-07-06",
		"order_id" : 3477,
		"lat" : "22.669011",
		"lon" : "88.438279",
		"courier_id" : "C3477",
		"customer_id" : "U668",
		"gps_ts" : "2025-07-06 01:29:00",
		"delivery_ts" : "2025-07-06 01:44:00",
		"sameday_delivery_status" : "Delivered"
	},
	{
		"sysrundate" : "2025-07-06",
		"order_id" : 3504,
		"lat" : "22.506291",
		"lon" : "88.318129",
		"courier_id" : "C3504",
		"customer_id" : "U457",
		"gps_ts" : "2025-07-06 09:43:00",
		"delivery_ts" : "2025-07-06 10:17:00",
		"sameday_delivery_status" : "Cancelled"
	},
	{
		"sysrundate" : "2025-07-06",
		"order_id" : 3588,
		"lat" : "22.560539",
		"lon" : "88.430739",
		"courier_id" : "C3588",
		"customer_id" : "U887",
		"gps_ts" : "2025-07-06 06:26:00",
		"delivery_ts" : "2025-07-06 06:33:00",
		"sameday_delivery_status" : "Cancelled"
	},
	{
		"sysrundate" : "2025-07-06",
		"order_id" : 3619,
		"lat" : "22.631524",
		"lon" : "88.352426",
		"courier_id" : "C3619",
		"customer_id" : "U286",
		"gps_ts" : "2025-07-06 05:50:00",
		"delivery_ts" : "2025-07-06 06:15:00",
		"sameday_delivery_status" : "Delivered"
	},
	{
		"sysrundate" : "2025-07-06",
		"order_id" : 3640,
		"lat" : "22.65007",
		"lon" : "88.418631",
		"courier_id" : "C3640",
		"customer_id" : "U455",
		"gps_ts" : "2025-07-06 00:40:00",
		"delivery_ts" : "2025-07-06 01:39:00",
		"sameday_delivery_status" : "Cancelled"
	},
	{
		"sysrundate" : "2025-07-06",
		"order_id" : 3737,
		"lat" : "22.544271",
		"lon" : "88.444432",
		"courier_id" : "C3737",
		"customer_id" : "U276",
		"gps_ts" : null,
		"delivery_ts" : null,
		"sameday_delivery_status" : "Not Started"
	},
	{
		"sysrundate" : "2025-07-06",
		"order_id" : 3776,
		"lat" : "22.580933",
		"lon" : "88.341554",
		"courier_id" : "C3776",
		"customer_id" : "U522",
		"gps_ts" : "2025-07-06 18:24:00",
		"delivery_ts" : "2025-07-06 18:23:00",
		"sameday_delivery_status" : "Ontheway"
	},
	{
		"sysrundate" : "2025-07-06",
		"order_id" : 3786,
		"lat" : "22.669077",
		"lon" : "88.325533",
		"courier_id" : "C3786",
		"customer_id" : "U772",
		"gps_ts" : null,
		"delivery_ts" : null,
		"sameday_delivery_status" : "Not Started"
	},
	{
		"sysrundate" : "2025-07-06",
		"order_id" : 3794,
		"lat" : "22.588975",
		"lon" : "88.318869",
		"courier_id" : "C3794",
		"customer_id" : "U265",
		"gps_ts" : "2025-07-06 02:15:00",
		"delivery_ts" : "2025-07-06 02:31:00",
		"sameday_delivery_status" : "Picked_up"
	},
	{
		"sysrundate" : "2025-07-06",
		"order_id" : 3858,
		"lat" : "22.652995",
		"lon" : "88.422832",
		"courier_id" : "C3858",
		"customer_id" : "U818",
		"gps_ts" : null,
		"delivery_ts" : null,
		"sameday_delivery_status" : "Not Started"
	},
	{
		"sysrundate" : "2025-07-06",
		"order_id" : 3915,
		"lat" : "22.531872",
		"lon" : "88.409729",
		"courier_id" : "C3915",
		"customer_id" : "U766",
		"gps_ts" : null,
		"delivery_ts" : null,
		"sameday_delivery_status" : "Not Started"
	},
	{
		"sysrundate" : "2025-07-06",
		"order_id" : 3937,
		"lat" : "22.690686",
		"lon" : "88.310514",
		"courier_id" : "C3937",
		"customer_id" : "U590",
		"gps_ts" : "2025-07-06 13:34:00",
		"delivery_ts" : "2025-07-06 13:54:00",
		"sameday_delivery_status" : "Picked_up"
	},
	{
		"sysrundate" : "2025-07-06",
		"order_id" : 4086,
		"lat" : "28.591635",
		"lon" : "76.854874",
		"courier_id" : "C4086",
		"customer_id" : "U795",
		"gps_ts" : null,
		"delivery_ts" : null,
		"sameday_delivery_status" : "Not Started"
	},
	{
		"sysrundate" : "2025-07-06",
		"order_id" : 4098,
		"lat" : "28.859729",
		"lon" : "77.296355",
		"courier_id" : "C4098",
		"customer_id" : "U409",
		"gps_ts" : null,
		"delivery_ts" : null,
		"sameday_delivery_status" : "Not Started"
	},
	{
		"sysrundate" : "2025-07-06",
		"order_id" : 4159,
		"lat" : "28.840988",
		"lon" : "77.135143",
		"courier_id" : "C4159",
		"customer_id" : "U925",
		"gps_ts" : "2025-07-06 18:18:00",
		"delivery_ts" : "2025-07-06 18:14:00",
		"sameday_delivery_status" : "Ontheway"
	},
	{
		"sysrundate" : "2025-07-06",
		"order_id" : 4170,
		"lat" : "28.617695",
		"lon" : "77.028235",
		"courier_id" : "C4170",
		"customer_id" : "U248",
		"gps_ts" : null,
		"delivery_ts" : null,
		"sameday_delivery_status" : "Not Started"
	},
	{
		"sysrundate" : "2025-07-06",
		"order_id" : 4184,
		"lat" : "28.583788",
		"lon" : "77.139283",
		"courier_id" : "C4184",
		"customer_id" : "U429",
		"gps_ts" : null,
		"delivery_ts" : null,
		"sameday_delivery_status" : "Not Started"
	},
	{
		"sysrundate" : "2025-07-06",
		"order_id" : 4261,
		"lat" : "28.471188",
		"lon" : "77.050944",
		"courier_id" : "C4261",
		"customer_id" : "U534",
		"gps_ts" : null,
		"delivery_ts" : null,
		"sameday_delivery_status" : "Not Started"
	},
	{
		"sysrundate" : "2025-07-06",
		"order_id" : 4262,
		"lat" : "28.658254",
		"lon" : "77.099918",
		"courier_id" : "C4262",
		"customer_id" : "U418",
		"gps_ts" : "2025-07-06 13:58:00",
		"delivery_ts" : "2025-07-06 14:30:00",
		"sameday_delivery_status" : "Cancelled"
	},
	{
		"sysrundate" : "2025-07-06",
		"order_id" : 4304,
		"lat" : "28.550866",
		"lon" : "76.897981",
		"courier_id" : "C4304",
		"customer_id" : "U656",
		"gps_ts" : "2025-07-06 04:58:00",
		"delivery_ts" : "2025-07-06 05:09:00",
		"sameday_delivery_status" : "Ontheway"
	},
	{
		"sysrundate" : "2025-07-06",
		"order_id" : 4315,
		"lat" : "28.401902",
		"lon" : "77.214042",
		"courier_id" : "C4315",
		"customer_id" : "U608",
		"gps_ts" : null,
		"delivery_ts" : null,
		"sameday_delivery_status" : "Not Started"
	},
	{
		"sysrundate" : "2025-07-06",
		"order_id" : 4414,
		"lat" : "28.590253",
		"lon" : "77.256768",
		"courier_id" : "C4414",
		"customer_id" : "U666",
		"gps_ts" : "2025-07-06 09:07:00",
		"delivery_ts" : "2025-07-06 09:00:00",
		"sameday_delivery_status" : "Ontheway"
	},
	{
		"sysrundate" : "2025-07-06",
		"order_id" : 4468,
		"lat" : "28.541753",
		"lon" : "77.206171",
		"courier_id" : "C4468",
		"customer_id" : "U629",
		"gps_ts" : null,
		"delivery_ts" : null,
		"sameday_delivery_status" : "Not Started"
	},
	{
		"sysrundate" : "2025-07-06",
		"order_id" : 4531,
		"lat" : "28.462328",
		"lon" : "77.186317",
		"courier_id" : "C4531",
		"customer_id" : "U794",
		"gps_ts" : null,
		"delivery_ts" : null,
		"sameday_delivery_status" : "Not Started"
	},
	{
		"sysrundate" : "2025-07-06",
		"order_id" : 4576,
		"lat" : "28.500023",
		"lon" : "77.315368",
		"courier_id" : "C4576",
		"customer_id" : "U205",
		"gps_ts" : "2025-07-06 03:13:00",
		"delivery_ts" : "2025-07-06 03:39:00",
		"sameday_delivery_status" : "Delivered"
	},
	{
		"sysrundate" : "2025-07-06",
		"order_id" : 4638,
		"lat" : "28.578662",
		"lon" : "76.946638",
		"courier_id" : "C4638",
		"customer_id" : "U279",
		"gps_ts" : "2025-07-06 14:24:00",
		"delivery_ts" : "2025-07-06 14:15:00",
		"sameday_delivery_status" : "Cancelled"
	},
	{
		"sysrundate" : "2025-07-06",
		"order_id" : 4702,
		"lat" : "28.544425",
		"lon" : "76.875447",
		"courier_id" : "C4702",
		"customer_id" : "U925",
		"gps_ts" : "2025-07-06 14:04:00",
		"delivery_ts" : "2025-07-06 15:01:00",
		"sameday_delivery_status" : "Delivered"
	},
	{
		"sysrundate" : "2025-07-06",
		"order_id" : 4721,
		"lat" : "28.416904",
		"lon" : "77.315582",
		"courier_id" : "C4721",
		"customer_id" : "U589",
		"gps_ts" : "2025-07-06 10:47:00",
		"delivery_ts" : "2025-07-06 10:47:00",
		"sameday_delivery_status" : "Cancelled"
	},
	{
		"sysrundate" : "2025-07-06",
		"order_id" : 4741,
		"lat" : "28.569124",
		"lon" : "77.100559",
		"courier_id" : "C4741",
		"customer_id" : "U948",
		"gps_ts" : "2025-07-06 03:54:00",
		"delivery_ts" : "2025-07-06 03:51:00",
		"sameday_delivery_status" : "Delivered"
	},
	{
		"sysrundate" : "2025-07-06",
		"order_id" : 4756,
		"lat" : "28.505828",
		"lon" : "76.951086",
		"courier_id" : "C4756",
		"customer_id" : "U281",
		"gps_ts" : null,
		"delivery_ts" : null,
		"sameday_delivery_status" : "Not Started"
	},
	{
		"sysrundate" : "2025-07-06",
		"order_id" : 4767,
		"lat" : "28.785191",
		"lon" : "77.256576",
		"courier_id" : "C4767",
		"customer_id" : "U251",
		"gps_ts" : "2025-07-06 04:58:00",
		"delivery_ts" : "2025-07-06 04:52:00",
		"sameday_delivery_status" : "Ontheway"
	},
	{
		"sysrundate" : "2025-07-06",
		"order_id" : 4815,
		"lat" : "28.837211",
		"lon" : "77.269501",
		"courier_id" : "C4815",
		"customer_id" : "U155",
		"gps_ts" : null,
		"delivery_ts" : null,
		"sameday_delivery_status" : "Not Started"
	},
	{
		"sysrundate" : "2025-07-06",
		"order_id" : 4843,
		"lat" : "28.486382",
		"lon" : "76.898579",
		"courier_id" : "C4843",
		"customer_id" : "U918",
		"gps_ts" : null,
		"delivery_ts" : null,
		"sameday_delivery_status" : "Not Started"
	},
	{
		"sysrundate" : "2025-07-06",
		"order_id" : 4850,
		"lat" : "28.497403",
		"lon" : "76.843876",
		"courier_id" : "C4850",
		"customer_id" : "U365",
		"gps_ts" : "2025-07-06 01:41:00",
		"delivery_ts" : "2025-07-06 02:10:00",
		"sameday_delivery_status" : "Cancelled"
	},
	{
		"sysrundate" : "2025-07-06",
		"order_id" : 4934,
		"lat" : "28.414236",
		"lon" : "77.062219",
		"courier_id" : "C4934",
		"customer_id" : "U705",
		"gps_ts" : "2025-07-06 08:27:00",
		"delivery_ts" : "2025-07-06 08:43:00",
		"sameday_delivery_status" : "Delivered"
	},
	{
		"sysrundate" : "2025-07-06",
		"order_id" : 4942,
		"lat" : "28.878601",
		"lon" : "77.037705",
		"courier_id" : "C4942",
		"customer_id" : "U966",
		"gps_ts" : "2025-07-06 16:19:00",
		"delivery_ts" : "2025-07-06 16:36:00",
		"sameday_delivery_status" : "Delivered"
	},
	{
		"sysrundate" : "2025-07-06",
		"order_id" : 4964,
		"lat" : "28.548983",
		"lon" : "77.015799",
		"courier_id" : "C4964",
		"customer_id" : "U768",
		"gps_ts" : "2025-07-06 01:08:00",
		"delivery_ts" : "2025-07-06 01:08:00",
		"sameday_delivery_status" : "Picked_up"
	},
	{
		"sysrundate" : "2025-07-06",
		"order_id" : 4965,
		"lat" : "28.449964",
		"lon" : "77.084729",
		"courier_id" : "C4965",
		"customer_id" : "U621",
		"gps_ts" : "2025-07-06 06:29:00",
		"delivery_ts" : "2025-07-06 06:47:00",
		"sameday_delivery_status" : "Delivered"
	},
	{
		"sysrundate" : "2025-07-06",
		"order_id" : 4994,
		"lat" : "28.463667",
		"lon" : "76.966483",
		"courier_id" : "C4994",
		"customer_id" : "U814",
		"gps_ts" : null,
		"delivery_ts" : null,
		"sameday_delivery_status" : "Not Started"
	},
	{
		"sysrundate" : "2025-07-06",
		"order_id" : 5050,
		"lat" : "22.733632",
		"lon" : "75.871718",
		"courier_id" : "C5050",
		"customer_id" : "U483",
		"gps_ts" : "2025-07-06 09:54:00",
		"delivery_ts" : "2025-07-06 10:09:00",
		"sameday_delivery_status" : "Ontheway"
	},
	{
		"sysrundate" : "2025-07-06",
		"order_id" : 5056,
		"lat" : "22.674438",
		"lon" : "75.848786",
		"courier_id" : "C5056",
		"customer_id" : "U633",
		"gps_ts" : null,
		"delivery_ts" : null,
		"sameday_delivery_status" : "Not Started"
	},
	{
		"sysrundate" : "2025-07-06",
		"order_id" : 5175,
		"lat" : "22.733289",
		"lon" : "75.85007",
		"courier_id" : "C5175",
		"customer_id" : "U254",
		"gps_ts" : null,
		"delivery_ts" : null,
		"sameday_delivery_status" : "Not Started"
	},
	{
		"sysrundate" : "2025-07-06",
		"order_id" : 5202,
		"lat" : "22.763093",
		"lon" : "75.908235",
		"courier_id" : "C5202",
		"customer_id" : "U536",
		"gps_ts" : "2025-07-06 08:05:00",
		"delivery_ts" : "2025-07-06 08:29:00",
		"sameday_delivery_status" : "Cancelled"
	},
	{
		"sysrundate" : "2025-07-06",
		"order_id" : 5339,
		"lat" : "22.682517",
		"lon" : "75.803105",
		"courier_id" : "C5339",
		"customer_id" : "U190",
		"gps_ts" : "2025-07-06 18:51:00",
		"delivery_ts" : "2025-07-06 18:41:00",
		"sameday_delivery_status" : "Delivered"
	},
	{
		"sysrundate" : "2025-07-06",
		"order_id" : 5442,
		"lat" : "22.757649",
		"lon" : "75.943017",
		"courier_id" : "C5442",
		"customer_id" : "U457",
		"gps_ts" : "2025-07-06 04:33:00",
		"delivery_ts" : "2025-07-06 04:57:00",
		"sameday_delivery_status" : "Ontheway"
	},
	{
		"sysrundate" : "2025-07-06",
		"order_id" : 5488,
		"lat" : "22.60798",
		"lon" : "75.825963",
		"courier_id" : "C5488",
		"customer_id" : "U861",
		"gps_ts" : "2025-07-06 12:06:00",
		"delivery_ts" : "2025-07-06 12:31:00",
		"sameday_delivery_status" : "Cancelled"
	},
	{
		"sysrundate" : "2025-07-06",
		"order_id" : 5508,
		"lat" : "22.769098",
		"lon" : "75.880644",
		"courier_id" : "C5508",
		"customer_id" : "U276",
		"gps_ts" : "2025-07-06 01:10:00",
		"delivery_ts" : "2025-07-06 01:55:00",
		"sameday_delivery_status" : "Cancelled"
	},
	{
		"sysrundate" : "2025-07-06",
		"order_id" : 5511,
		"lat" : "22.693126",
		"lon" : "75.890614",
		"courier_id" : "C5511",
		"customer_id" : "U339",
		"gps_ts" : "2025-07-06 19:13:00",
		"delivery_ts" : "2025-07-06 19:05:00",
		"sameday_delivery_status" : "Picked_up"
	},
	{
		"sysrundate" : "2025-07-06",
		"order_id" : 5575,
		"lat" : "22.658302",
		"lon" : "75.925945",
		"courier_id" : "C5575",
		"customer_id" : "U508",
		"gps_ts" : "2025-07-06 10:34:00",
		"delivery_ts" : "2025-07-06 10:58:00",
		"sameday_delivery_status" : "Cancelled"
	},
	{
		"sysrundate" : "2025-07-06",
		"order_id" : 5577,
		"lat" : "22.769202",
		"lon" : "75.797869",
		"courier_id" : "C5577",
		"customer_id" : "U287",
		"gps_ts" : "2025-07-06 00:37:00",
		"delivery_ts" : "2025-07-06 00:48:00",
		"sameday_delivery_status" : "Delivered"
	},
	{
		"sysrundate" : "2025-07-06",
		"order_id" : 5581,
		"lat" : "22.673078",
		"lon" : "75.838257",
		"courier_id" : "C5581",
		"customer_id" : "U963",
		"gps_ts" : null,
		"delivery_ts" : null,
		"sameday_delivery_status" : "Not Started"
	},
	{
		"sysrundate" : "2025-07-06",
		"order_id" : 5616,
		"lat" : "22.70901",
		"lon" : "75.863567",
		"courier_id" : "C5616",
		"customer_id" : "U702",
		"gps_ts" : null,
		"delivery_ts" : null,
		"sameday_delivery_status" : "Not Started"
	},
	{
		"sysrundate" : "2025-07-06",
		"order_id" : 5691,
		"lat" : "22.601391",
		"lon" : "75.81393",
		"courier_id" : "C5691",
		"customer_id" : "U512",
		"gps_ts" : "2025-07-06 07:06:00",
		"delivery_ts" : "2025-07-06 06:58:00",
		"sameday_delivery_status" : "Delivered"
	},
	{
		"sysrundate" : "2025-07-06",
		"order_id" : 5717,
		"lat" : "22.617029",
		"lon" : "75.755292",
		"courier_id" : "C5717",
		"customer_id" : "U437",
		"gps_ts" : null,
		"delivery_ts" : null,
		"sameday_delivery_status" : "Not Started"
	},
	{
		"sysrundate" : "2025-07-06",
		"order_id" : 5772,
		"lat" : "22.752335",
		"lon" : "75.816983",
		"courier_id" : "C5772",
		"customer_id" : "U424",
		"gps_ts" : null,
		"delivery_ts" : null,
		"sameday_delivery_status" : "Not Started"
	},
	{
		"sysrundate" : "2025-07-06",
		"order_id" : 5777,
		"lat" : "22.69211",
		"lon" : "75.90594",
		"courier_id" : "C5777",
		"customer_id" : "U260",
		"gps_ts" : "2025-07-06 09:06:00",
		"delivery_ts" : "2025-07-06 09:38:00",
		"sameday_delivery_status" : "Ontheway"
	},
	{
		"sysrundate" : "2025-07-06",
		"order_id" : 5809,
		"lat" : "22.758365",
		"lon" : "75.792551",
		"courier_id" : "C5809",
		"customer_id" : "U681",
		"gps_ts" : "2025-07-06 01:24:00",
		"delivery_ts" : "2025-07-06 01:23:00",
		"sameday_delivery_status" : "Cancelled"
	},
	{
		"sysrundate" : "2025-07-06",
		"order_id" : 5822,
		"lat" : "22.711572",
		"lon" : "75.804123",
		"courier_id" : "C5822",
		"customer_id" : "U230",
		"gps_ts" : "2025-07-06 01:24:00",
		"delivery_ts" : "2025-07-06 01:17:00",
		"sameday_delivery_status" : "Delivered"
	},
	{
		"sysrundate" : "2025-07-06",
		"order_id" : 5866,
		"lat" : "22.72971",
		"lon" : "75.888958",
		"courier_id" : "C5866",
		"customer_id" : "U598",
		"gps_ts" : null,
		"delivery_ts" : null,
		"sameday_delivery_status" : "Not Started"
	},
	{
		"sysrundate" : "2025-07-06",
		"order_id" : 5867,
		"lat" : "22.747215",
		"lon" : "75.776063",
		"courier_id" : "C5867",
		"customer_id" : "U619",
		"gps_ts" : "2025-07-06 18:02:00",
		"delivery_ts" : "2025-07-06 18:26:00",
		"sameday_delivery_status" : "Cancelled"
	},
	{
		"sysrundate" : "2025-07-06",
		"order_id" : 5880,
		"lat" : "22.706892",
		"lon" : "75.752899",
		"courier_id" : "C5880",
		"customer_id" : "U222",
		"gps_ts" : null,
		"delivery_ts" : null,
		"sameday_delivery_status" : "Not Started"
	},
	{
		"sysrundate" : "2025-07-06",
		"order_id" : 5882,
		"lat" : "22.726049",
		"lon" : "75.902958",
		"courier_id" : "C5882",
		"customer_id" : "U979",
		"gps_ts" : "2025-07-06 18:57:00",
		"delivery_ts" : "2025-07-06 19:24:00",
		"sameday_delivery_status" : "Delivered"
	},
	{
		"sysrundate" : "2025-07-06",
		"order_id" : 5897,
		"lat" : "22.770838",
		"lon" : "75.935838",
		"courier_id" : "C5897",
		"customer_id" : "U981",
		"gps_ts" : "2025-07-06 07:52:00",
		"delivery_ts" : "2025-07-06 08:49:00",
		"sameday_delivery_status" : "Cancelled"
	},
	{
		"sysrundate" : "2025-07-06",
		"order_id" : 5905,
		"lat" : "22.659407",
		"lon" : "75.750451",
		"courier_id" : "C5905",
		"customer_id" : "U461",
		"gps_ts" : null,
		"delivery_ts" : null,
		"sameday_delivery_status" : "Not Started"
	},
	{
		"sysrundate" : "2025-07-06",
		"order_id" : 5932,
		"lat" : "22.659336",
		"lon" : "75.813833",
		"courier_id" : "C5932",
		"customer_id" : "U963",
		"gps_ts" : "2025-07-06 03:55:00",
		"delivery_ts" : "2025-07-06 04:22:00",
		"sameday_delivery_status" : "Cancelled"
	},
	{
		"sysrundate" : "2025-07-06",
		"order_id" : 5939,
		"lat" : "22.773337",
		"lon" : "75.819202",
		"courier_id" : "C5939",
		"customer_id" : "U396",
		"gps_ts" : "2025-07-06 15:18:00",
		"delivery_ts" : "2025-07-06 15:45:00",
		"sameday_delivery_status" : "Delivered"
	},
	{
		"sysrundate" : "2025-07-06",
		"order_id" : 5957,
		"lat" : "22.699201",
		"lon" : "75.764173",
		"courier_id" : "C5957",
		"customer_id" : "U251",
		"gps_ts" : "2025-07-06 04:35:00",
		"delivery_ts" : "2025-07-06 04:34:00",
		"sameday_delivery_status" : "Delivered"
	},
	{
		"sysrundate" : "2025-07-06",
		"order_id" : 5977,
		"lat" : "22.628181",
		"lon" : "75.897268",
		"courier_id" : "C5977",
		"customer_id" : "U220",
		"gps_ts" : "2025-07-06 11:49:00",
		"delivery_ts" : "2025-07-06 11:57:00",
		"sameday_delivery_status" : "Delivered"
	},
	{
		"sysrundate" : "2025-07-06",
		"order_id" : 5996,
		"lat" : "22.673614",
		"lon" : "75.789764",
		"courier_id" : "C5996",
		"customer_id" : "U797",
		"gps_ts" : "2025-07-06 04:29:00",
		"delivery_ts" : "2025-07-06 04:27:00",
		"sameday_delivery_status" : "Delivered"
	}
]
